pyshell/__init__.py
pyshell/shell.py
pyshell/test_module.py
unix_pyshell_pybc2-0.0.1.dist-info/METADATA
unix_pyshell_pybc2-0.0.1.dist-info/WHEEL
unix_pyshell_pybc2-0.0.1.dist-info/top_level.txt
unix_pyshell_pybc2-0.0.1.dist-info/RECORD
